whoisquery/__init__.py
whoisquery/cli.py
whoisquery/core.py
WhoisQuery-0.1.4.dist-info/LICENSE
WhoisQuery-0.1.4.dist-info/METADATA
WhoisQuery-0.1.4.dist-info/WHEEL
WhoisQuery-0.1.4.dist-info/entry_points.txt
WhoisQuery-0.1.4.dist-info/top_level.txt
WhoisQuery-0.1.4.dist-info/RECORD
