Metadata-Version: 2.1
Name: WhoisQuery
Version: 0.1.4
Summary: A simple and efficient WHOIS lookup library for Python
Author-email: Yoandy Isse Oña <yoandysse@gmail.com>
License: MIT License
Project-URL: Homepage, https://github.com/yoandysse/WhoisQuery
Project-URL: Repository, https://github.com/yoandysse/WhoisQuery
Project-URL: Issues, https://github.com/yoandysse/whoisquery/issues
Project-URL: Bug Tracker, https://github.com/yoandysse/whoisquery/issues
Keywords: whois,lookup,library,python
Classifier: Development Status :: 3 - Alpha
Classifier: Intended Audience :: Developers
Classifier: Intended Audience :: System Administrators
Classifier: Intended Audience :: Telecommunications Industry
Classifier: License :: OSI Approved :: MIT License
Classifier: Programming Language :: Python :: 3
Classifier: Operating System :: OS Independent
License-File: LICENSE
Provides-Extra: test
Requires-Dist: pytest>=7.0; extra == "test"
Requires-Dist: pytest-cov>=4.0; extra == "test"
Requires-Dist: pytest-mock>=3.10; extra == "test"
